oauth_api/__init__.py
oauth_api/admin.py
oauth_api/apps.py
oauth_api/authentication.py
oauth_api/exceptions.py
oauth_api/forms.py
oauth_api/generators.py
oauth_api/handlers.py
oauth_api/mixins.py
oauth_api/models.py
oauth_api/permissions.py
oauth_api/settings.py
oauth_api/urls.py
oauth_api/utils.py
oauth_api/validators.py
oauth_api/views.py
oauth_api/migrations/0001_initial.py
oauth_api/migrations/0002_auto_20150904_1155.py
oauth_api/migrations/0003_auto_20160331_1731.py
oauth_api/migrations/0004_alter_accesstoken_id_alter_application_id_and_more.py
oauth_api/migrations/0005_alter_authorizationcode_code_alter_refreshtoken_token.py
oauth_api/migrations/0006_alter_accesstoken_token_alter_authorizationcode_code_and_more.py
oauth_api/migrations/__init__.py
oauth_api/templates/oauth_api/authorize.html
oauth_api/templates/oauth_api/base.html
oauth_api/tests/__init__.py
oauth_api/tests/settings.py
oauth_api/tests/test_authorization_code.py
oauth_api/tests/test_client_credentials.py
oauth_api/tests/test_generators.py
oauth_api/tests/test_implicit.py
oauth_api/tests/test_models.py
oauth_api/tests/test_resource_owner.py
oauth_api/tests/test_scopes.py
oauth_api/tests/test_token_revocation.py
oauth_api/tests/test_utils.py
oauth_api/tests/urls.py
oauth_api/tests/utils.py
oauth_api/tests/views.py
django_oauth_api-0.9.0.dist-info/LICENSE
django_oauth_api-0.9.0.dist-info/METADATA
django_oauth_api-0.9.0.dist-info/WHEEL
django_oauth_api-0.9.0.dist-info/top_level.txt
django_oauth_api-0.9.0.dist-info/RECORD
