Metadata-Version: 2.1
Name: django-oauth-api
Version: 0.9.0
Summary: OAuth API for Django using Django Rest Framework
Home-page: https://github.com/eofs/django-oauth-api
Author: Tomi Pajunen
Author-email: tomi@madlab.fi
License: BSD
Keywords: django djangorestframework oauth oauth2 oauthlib
Classifier: Development Status :: 4 - Beta
Classifier: Environment :: Web Environment
Classifier: Framework :: Django
Classifier: License :: OSI Approved :: BSD License
Classifier: Operating System :: OS Independent
Classifier: Programming Language :: Python :: 3.8
Classifier: Programming Language :: Python :: 3.9
Classifier: Programming Language :: Python :: 3.10
Classifier: Framework :: Django
Classifier: Framework :: Django :: 3.2
Classifier: Framework :: Django :: 4.0
Classifier: Framework :: Django :: 4.1
Classifier: Topic :: Software Development :: Libraries :: Python Modules
Requires-Python: >=3.8
License-File: LICENSE
Requires-Dist: djangorestframework (>=3.14.0)
Requires-Dist: oauthlib (==3.2.2)
